src/__init__.py
src/__main__.py
src/data/ignore.dat
src/data/projects.dat
src/data/sessions.dat
src/data/trackdata.dat
src/trak/__init__.py
src/trak/afile.py
src/trak/core_methods.py
src/trak/project.py
src/trak/session.py
trak-0.1.2.dist-info/LICENSE
trak-0.1.2.dist-info/METADATA
trak-0.1.2.dist-info/WHEEL
trak-0.1.2.dist-info/entry_points.txt
trak-0.1.2.dist-info/top_level.txt
trak-0.1.2.dist-info/RECORD
