Metadata-Version: 2.1
Name: trak
Version: 0.1.2
Summary: A simple writing-progress tracking tool for plain text files
Home-page: UNKNOWN
Author: Greg Pyle
Author-email: chaoborid@gmail.com
License: UNKNOWN
Download-URL: https://github.com/Gambusia/trak
Platform: UNKNOWN
Classifier: Development Status :: 4 - Beta
Classifier: Environment :: Console
Classifier: Intended Audience :: End Users/Desktop
Classifier: License :: OSI Approved :: MIT License
Classifier: Operating System :: OS Independent
Classifier: Programming Language :: Python
Classifier: Topic :: Office/Business
Classifier: Topic :: Text Editors :: Text Processing
Classifier: Topic :: Text Processing :: General
Classifier: Topic :: Utilities
Classifier: Typing :: Typed
License-File: LICENSE
Requires-Dist: tabulate
